arcanna_mcp_input_server/__init__.py
arcanna_mcp_input_server/constants.py
arcanna_mcp_input_server/environment.py
arcanna_mcp_input_server/server.py
arcanna_mcp_input_server/tools/__init__.py
arcanna_mcp_input_server/tools/events.py
arcanna_mcp_input_server/tools/health_check.py
arcanna_mcp_input_server/tools/jobs.py
arcanna_mcp_input_server/utils/__init__.py
arcanna_mcp_input_server/utils/exceptions_handler.py
arcanna_mcp_input_server/utils/tool_exception_response.py
arcanna_mcp_input_server-0.0.6.dist-info/METADATA
arcanna_mcp_input_server-0.0.6.dist-info/WHEEL
arcanna_mcp_input_server-0.0.6.dist-info/entry_points.txt
arcanna_mcp_input_server-0.0.6.dist-info/licenses/LICENSE
arcanna_mcp_input_server-0.0.6.dist-info/RECORD
