Metadata-Version: 2.4
Name: arcanna-mcp-input-server
Version: 0.0.6
Summary: The Arcanna MCP Input server allows user to send data and feedback to  AI use cases through the Model Context Protocol (MCP).
Project-URL: homepage, https://github.com/siscale/arcanna-mcp-input-server
Author-email: DevSiscale <dev@siscale.com>
License-File: LICENSE
Requires-Python: >=3.10
Requires-Dist: fastapi>=0.115.6
Requires-Dist: mcp[cli]>=1.2.1
Requires-Dist: requests>=2.32.3
Requires-Dist: starlette>=0.46.0
Requires-Dist: uv>=0.6.9
